{
	"id": "a3618a03-2b62-e3f8-b8fe-4f3379501a8e",
	"name": "AutoComplete",
	"description": "",
	"order": [
		"1706141f-1bd3-e6b5-4925-b7c1247b279d",
		"eb4eb52c-7312-cafc-0e68-89bfe30a649d",
		"8080ffaa-c757-456f-0b81-0446a731f931",
		"bd9ec882-b538-48b0-adbe-cfa2820cef92",
		"f4d20523-9f29-c8b8-a747-372687f84be8",
		"4a791c70-f75c-6e01-70c3-b9ff8d73dbdc"
	],
	"folders": [],
	"folders_order": [],
	"timestamp": 1592643616065,
	"owner": 0,
	"public": false,
	"requests": [
		{
			"id": "1706141f-1bd3-e6b5-4925-b7c1247b279d",
			"headers": "Authorization: Basic cG93ZXJTY2hvb2w6cGFzc3dvcmRGb3IyMDIw\n",
			"headerData": [
				{
					"key": "Authorization",
					"value": "Basic cG93ZXJTY2hvb2w6cGFzc3dvcmRGb3IyMDIw",
					"description": "",
					"enabled": true
				}
			],
			"url": "http://localhost:8080/course/clearAllCourses",
			"queryParams": [],
			"preRequestScript": null,
			"pathVariables": {},
			"pathVariableData": [],
			"method": "DELETE",
			"data": null,
			"dataMode": "params",
			"tests": null,
			"currentHelper": "normal",
			"helperAttributes": {},
			"time": 1592706410053,
			"name": "Delete all Courses",
			"description": "",
			"collectionId": "a3618a03-2b62-e3f8-b8fe-4f3379501a8e",
			"responses": []
		},
		{
			"id": "4a791c70-f75c-6e01-70c3-b9ff8d73dbdc",
			"headers": "",
			"headerData": [],
			"url": "http://localhost:8080/course/delete/1",
			"queryParams": [],
			"pathVariables": {},
			"pathVariableData": [],
			"preRequestScript": null,
			"method": "DELETE",
			"collectionId": "a3618a03-2b62-e3f8-b8fe-4f3379501a8e",
			"data": null,
			"dataMode": "params",
			"name": "Delete Course",
			"description": "",
			"descriptionFormat": "html",
			"time": 1592707673971,
			"version": 2,
			"responses": [],
			"tests": null,
			"currentHelper": "normal",
			"helperAttributes": {}
		},
		{
			"id": "8080ffaa-c757-456f-0b81-0446a731f931",
			"headers": "",
			"headerData": [],
			"url": "http://localhost:8080/course/read/1",
			"queryParams": [],
			"pathVariables": {},
			"pathVariableData": [],
			"preRequestScript": null,
			"method": "GET",
			"collectionId": "a3618a03-2b62-e3f8-b8fe-4f3379501a8e",
			"data": null,
			"dataMode": "params",
			"name": "Read Course",
			"description": "",
			"descriptionFormat": "html",
			"time": 1592644617583,
			"version": 2,
			"responses": [],
			"tests": null,
			"currentHelper": "normal",
			"helperAttributes": {}
		},
		{
			"id": "bd9ec882-b538-48b0-adbe-cfa2820cef92",
			"headers": "",
			"headerData": [],
			"url": "http://localhost:8080/course/search/exactMatch/name/Java 8",
			"queryParams": [],
			"preRequestScript": null,
			"pathVariables": {},
			"pathVariableData": [],
			"method": "GET",
			"data": null,
			"dataMode": "params",
			"tests": null,
			"currentHelper": "normal",
			"helperAttributes": {},
			"time": 1592709604023,
			"name": "Get Course By Name Exact Match",
			"description": "",
			"collectionId": "a3618a03-2b62-e3f8-b8fe-4f3379501a8e",
			"responses": []
		},
		{
			"id": "eb4eb52c-7312-cafc-0e68-89bfe30a649d",
			"headers": "Content-Type: application/json\n",
			"headerData": [
				{
					"key": "Content-Type",
					"value": "application/json",
					"description": "",
					"enabled": true
				}
			],
			"url": "http://localhost:8080/course",
			"queryParams": [],
			"preRequestScript": null,
			"pathVariables": {},
			"pathVariableData": [],
			"method": "POST",
			"data": [],
			"dataMode": "raw",
			"tests": null,
			"currentHelper": "normal",
			"helperAttributes": {},
			"time": 1592709564438,
			"name": "Create Course",
			"description": "",
			"collectionId": "a3618a03-2b62-e3f8-b8fe-4f3379501a8e",
			"responses": [],
			"rawModeData": "{\n    \"courseId\": 102,\n    \"courseName\": \"Java P\",\n    \"courseDescription\": \"Intro\",\n    \"instructorName\": \"Terry\",\n    \"gradeLevel\": 1\n}"
		},
		{
			"id": "f4d20523-9f29-c8b8-a747-372687f84be8",
			"headers": "",
			"headerData": [],
			"url": "http://localhost:8080/course/search/name/jav",
			"queryParams": [],
			"preRequestScript": null,
			"pathVariables": {},
			"pathVariableData": [],
			"method": "GET",
			"data": null,
			"dataMode": "params",
			"tests": null,
			"currentHelper": "normal",
			"helperAttributes": {},
			"time": 1592710567921,
			"name": "Autocomplete Api Search",
			"description": "",
			"collectionId": "a3618a03-2b62-e3f8-b8fe-4f3379501a8e",
			"responses": []
		}
	]
}